athena_udf/__init__.py
athena_udf-0.2.dist-info/LICENSE
athena_udf-0.2.dist-info/METADATA
athena_udf-0.2.dist-info/WHEEL
athena_udf-0.2.dist-info/top_level.txt
athena_udf-0.2.dist-info/RECORD
