Metadata-Version: 2.1
Name: athena-udf
Version: 0.2
Summary: Athena User Defined Functions(UDFs) made easy!
Home-page: https://github.com/dmarkey/python-athena-udf
Author: David Markey
License: Apache License, Version 2.0
Project-URL: Issues, https://github.com/dmarkey/python-athena-udf/issues
Project-URL: CI, https://github.com/dmarkey/python-athena-udf/actions
Project-URL: Changelog, https://github.com/dmarkey/python-athena-udf/releases
Requires-Python: >=3.7
License-File: LICENSE
Requires-Dist: pyarrow (>10.0.0)
Provides-Extra: test
Requires-Dist: pytest ; extra == 'test'
